wrapper/__init__.py
wrapper/getHeaders.py
python_roblox_api_wrapper-0.0.1.dist-info/LICENSE
python_roblox_api_wrapper-0.0.1.dist-info/METADATA
python_roblox_api_wrapper-0.0.1.dist-info/WHEEL
python_roblox_api_wrapper-0.0.1.dist-info/top_level.txt
python_roblox_api_wrapper-0.0.1.dist-info/RECORD
